{
	"credit": "Made with Blockbench",
	"parent": "create:item/package_transforms",
	"textures": {
		"0": "create:entity/package/cardboard",
		"particle": "create:entity/package/cardboard_particle"
	},
	"elements": [
		{
			"from": [3, 0, 3],
			"to": [13, 8, 13],
			"faces": {
				"north": {"uv": [9.25, 3, 11.75, 5], "texture": "#0"},
				"east": {"uv": [6.75, 0.5, 9.25, 2.5], "texture": "#0"},
				"south": {"uv": [9.25, 3, 11.75, 5], "texture": "#0"},
				"west": {"uv": [6.75, 2.5, 9.25, 4.5], "texture": "#0"},
				"up": {"uv": [9.25, 0.5, 11.75, 3], "texture": "#0"},
				"down": {"uv": [6.75, 4.5, 9.25, 7], "texture": "#0"}
			}
		}
	]
}